tests/__init__.py
tests/unit/__init__.py
tests/unit/features/__init__.py
tests/unit/features/test_diagnostics.py
textx_ls_server/__init__.py
textx_ls_server/__main__.py
textx_ls_server/config.py
textx_ls_server/protocol.py
textx_ls_server/server.py
textx_ls_server/utils.py
textx_ls_server/features/__init__.py
textx_ls_server/features/diagnostics.py
textx_ls_server-0.2.0.dist-info/METADATA
textx_ls_server-0.2.0.dist-info/WHEEL
textx_ls_server-0.2.0.dist-info/top_level.txt
textx_ls_server-0.2.0.dist-info/RECORD
